ci_rvm/__ci_rvm_mpinv.py
ci_rvm/__init__.py
ci_rvm/ci_rvm.py
ci_rvm/ci_rvm_mpinv.py
ci_rvm/test_ci_rvm.py
ci_rvm-0.10.1b3.dist-info/LICENSE
ci_rvm-0.10.1b3.dist-info/METADATA
ci_rvm-0.10.1b3.dist-info/WHEEL
ci_rvm-0.10.1b3.dist-info/top_level.txt
ci_rvm-0.10.1b3.dist-info/RECORD
