Metadata-Version: 2.1
Name: ci-rvm
Version: 0.10.1b3
Summary: An algorithm to find profile likelihood confidence intervals
Home-page: https://github.com/vemomoto/vemomoto
Author: Samuel M. Fischer
License: LGPLv3
Project-URL: Bug Tracker, https://github.com/vemomoto/vemomoto/issues
Project-URL: Documentation, https://vemomoto.github.io/ci_rvm
Project-URL: Source Code, https://github.com/vemomoto/vemomoto/tree/master/ci_rvm
Project-URL: Publication, https://link.springer.com/article/10.1007/s11222-021-10012-y
Keywords: confidence interval,likelihood,profile likelihood
Classifier: License :: OSI Approved :: GNU Lesser General Public License v3 (LGPLv3)
Classifier: Development Status :: 4 - Beta
Classifier: Intended Audience :: Science/Research
Requires-Python: >=3.6
License-File: LICENSE
Requires-Dist: numpy
Requires-Dist: scipy
Requires-Dist: vemomoto-core-tools
Requires-Dist: numdifftools
